LICENSE
setup.cfg
setup.py
Optimizers/__init__.py
Optimizers/config.py
Optimizers/examples.py
Optimizers/optimizers.py
Optimizers.egg-info/PKG-INFO
Optimizers.egg-info/SOURCES.txt
Optimizers.egg-info/dependency_links.txt
Optimizers.egg-info/requires.txt
Optimizers.egg-info/top_level.txt