Metadata-Version: 2.1
Name: Optimizers
Version: 0.1
Summary: A collection of examples for learning mathematical modelling
Home-page: https://github.com/davidswlai/
Download-URL: https://github.com/davidswlai/Optimizers/releases/latest
Author: David S.W. Lai
Author-email: david.lai@soton.ac.uk
License: GNU General Public License v3.0
Keywords: Optimizers,Mathematical Optimization,Operations Research,Logistics,Routing,Scheduling
Classifier: Development Status :: 3 - Alpha
Classifier: Intended Audience :: Developers
Classifier: Topic :: Software Development :: Build Tools
Classifier: License :: OSI Approved :: MIT License
Classifier: Programming Language :: Python :: 3
Classifier: Programming Language :: Python :: 3.4
Classifier: Programming Language :: Python :: 3.5
Classifier: Programming Language :: Python :: 3.6
Classifier: Programming Language :: Python :: 3.7
Classifier: Programming Language :: Python :: 3.8
License-File: LICENSE
